{
  "users": [
    {
      "id": "23",
      "firstName": "Bill",
      "age": "22",
      "companyId": "1"
    },
    {
      "id": "25",
      "firstName": "Chris",
      "age": "30",
      "companyId": "2"
    },
    {
      "id": "30",
      "firstName": "Mike",
      "age": "33",
      "companyId": "2"
    },
    {
      "firstName": "Myron",
      "age": 26,
      "id": "BJGwXc9lW"
    },
    {
      "firstName": "Myron",
      "age": 26,
      "id": "S1bmI9ql-"
    },
    {
      "firstName": "Myron",
      "age": 26,
      "id": "BJ8XL95xW"
    },
    {
      "firstName": "Myron",
      "age": 26,
      "id": "HknQLqcl-"
    },
    {
      "firstName": "Myron",
      "age": 26,
      "id": "S1bNI99lZ"
    },
    {
      "firstName": "Ryan",
      "age": 13,
      "id": "SJ_HUc9gb"
    }
  ],
  "companies": [
    {
      "id": "1",
      "nanme": "Apple",
      "description": "iphone"
    },
    {
      "id": "2",
      "name": "Google",
      "description": "search"
    }
  ]
}